repo2ai/__init__.py
repo2ai/browser.py
repo2ai/cli.py
repo2ai/core.py
repo2ai/output.py
repo2ai/pr.py
repo2ai/scope.py
repo2ai-0.2.4.dist-info/METADATA
repo2ai-0.2.4.dist-info/WHEEL
repo2ai-0.2.4.dist-info/entry_points.txt
repo2ai-0.2.4.dist-info/licenses/LICENSE
repo2ai-0.2.4.dist-info/RECORD
