Metadata-Version: 2.4
Name: repo2ai
Version: 0.2.4
Summary: Export Git repository contents to structured Markdown with AI chat integration
License: MIT
License-File: LICENSE
Keywords: markdown,documentation,git,repository,export,ai-chat
Author: Georg Hildebrand
Author-email: your-email@example.com
Requires-Python: >=3.11,<4.0
Classifier: Development Status :: 4 - Beta
Classifier: Environment :: Console
Classifier: Intended Audience :: Developers
Classifier: License :: OSI Approved :: MIT License
Classifier: Operating System :: OS Independent
Classifier: Programming Language :: Python :: 3
Classifier: Programming Language :: Python :: 3.11
Classifier: Programming Language :: Python :: 3.12
Classifier: Programming Language :: Python :: 3.13
Classifier: Programming Language :: Python :: 3.14
Classifier: Topic :: Documentation
Classifier: Topic :: Software Development :: Documentation
Classifier: Topic :: Text Processing :: Markup :: Markdown
Requires-Dist: pre-commit (>=4.5.1,<5.0.0)
Requires-Dist: pyperclip (>=1.8.0,<2.0.0)
Requires-Dist: twine (>=6.1.0,<7.0.0)
Project-URL: Bug Tracker, https://github.com/georghildebrand/repo2ai/issues
Project-URL: Changelog, https://github.com/georghildebrand/repo2ai/releases
Project-URL: Documentation, https://github.com/georghildebrand/repo2ai#readme
Project-URL: Homepage, https://github.com/georghildebrand/repo2ai
Project-URL: Repository, https://github.com/georghildebrand/repo2ai
